pdf_table2json/__init__.py
pdf_table2json/converter.py
pdf_table2json/converter_2.py
pdf_table2json/merge.py
pdf_table2json/test.py
pdf_table2json/test_local.py
pdf_table2json/util.py
pdf_table2json-2.0.1.dist-info/LICENSE
pdf_table2json-2.0.1.dist-info/METADATA
pdf_table2json-2.0.1.dist-info/WHEEL
pdf_table2json-2.0.1.dist-info/top_level.txt
pdf_table2json-2.0.1.dist-info/zip-safe
pdf_table2json-2.0.1.dist-info/RECORD
